com/github/piotr_yuxuan/__init__.py
com/github/piotr_yuxuan/cte2dbt.py
cte2dbt-1.0.5.dist-info/LICENSE
cte2dbt-1.0.5.dist-info/METADATA
cte2dbt-1.0.5.dist-info/WHEEL
cte2dbt-1.0.5.dist-info/RECORD
