Metadata-Version: 2.3
Name: cte2dbt
Version: 1.0.5
Summary: Tools with batteries included to extract CTE from a large SQL query and split them iteratively into dbt models.
License: EUPL-1.2
Keywords: sql,sqlglot,data,dbt,models,cte
Author: piotr-yuxuan
Author-email: piotr-yuxuan@users.noreply.github.com
Requires-Python: >=3.8.1,<4.0
Classifier: Development Status :: 5 - Production/Stable
Classifier: Intended Audience :: Developers
Classifier: License :: OSI Approved :: European Union Public Licence 1.2 (EUPL 1.2)
Classifier: Programming Language :: Python :: 3
Classifier: Programming Language :: Python :: 3.9
Classifier: Programming Language :: Python :: 3.10
Classifier: Programming Language :: Python :: 3.11
Classifier: Programming Language :: Python :: 3.12
Classifier: Programming Language :: Python :: 3.13
Classifier: Programming Language :: Python :: 3.8
Classifier: Topic :: Database
Classifier: Topic :: Software Development :: Libraries
Classifier: Typing :: Typed
Project-URL: Repository, https://github.com/piotr-yuxuan/cte2dbt
